Metadata-Version: 1.2
Name: scikit-garden-forked
Version: 0.0.2
Summary: A garden of scikit-learn compatible trees, and I had few modifications to it.
Home-page: https://github.com/Demangio/scikit-garden
Maintainer: Guillaume
Maintainer-email: guillaumedemange@free.fr
License: new BSD
Platform: UNKNOWN
Classifier: Intended Audience :: Science/Research
Classifier: Intended Audience :: Developers
Classifier: License :: OSI Approved
Classifier: Programming Language :: C
Classifier: Programming Language :: Python
Classifier: Topic :: Software Development
Classifier: Topic :: Scientific/Engineering
Classifier: Operating System :: Microsoft :: Windows
Classifier: Operating System :: POSIX
Classifier: Operating System :: Unix
Classifier: Operating System :: MacOS
